pyfock/Basis.py
pyfock/DFT.py
pyfock/DFT_Helper_Coulomb.py
pyfock/Data.py
pyfock/Graphics.py
pyfock/Graphics_old.py
pyfock/Grids.py
pyfock/HF.py
pyfock/Integrals_.py
pyfock/Mol.py
pyfock/PBC_ring.py
pyfock/UHF_atoms.py
pyfock/__init__.py
pyfock/densfuncs.py
pyfock/BasisSets/2zapa-nr-cv.0.ref.bib
pyfock/BasisSets/2zapa-nr-cv.0.tm
pyfock/BasisSets/2zapa-nr-cv.1.ref.bib
pyfock/BasisSets/2zapa-nr-cv.1.tm
pyfock/BasisSets/2zapa-nr-cv.notes
pyfock/BasisSets/2zapa-nr.0.ref.bib
pyfock/BasisSets/2zapa-nr.0.tm
pyfock/BasisSets/2zapa-nr.1.ref.bib
pyfock/BasisSets/2zapa-nr.1.tm
pyfock/BasisSets/2zapa-nr.notes
pyfock/BasisSets/3-21g.0.ref.bib
pyfock/BasisSets/3-21g.0.tm
pyfock/BasisSets/3-21g.1.ref.bib
pyfock/BasisSets/3-21g.1.tm
pyfock/BasisSets/3-21g.notes
pyfock/BasisSets/3zapa-nr-cv.0.ref.bib
pyfock/BasisSets/3zapa-nr-cv.0.tm
pyfock/BasisSets/3zapa-nr-cv.1.ref.bib
pyfock/BasisSets/3zapa-nr-cv.1.tm
pyfock/BasisSets/3zapa-nr-cv.notes
pyfock/BasisSets/3zapa-nr.0.ref.bib
pyfock/BasisSets/3zapa-nr.0.tm
pyfock/BasisSets/3zapa-nr.1.ref.bib
pyfock/BasisSets/3zapa-nr.1.tm
pyfock/BasisSets/3zapa-nr.notes
pyfock/BasisSets/4-31g.0.ref.bib
pyfock/BasisSets/4-31g.0.tm
pyfock/BasisSets/4-31g.1.ref.bib
pyfock/BasisSets/4-31g.1.tm
pyfock/BasisSets/4-31g.notes
pyfock/BasisSets/4zapa-nr-cv.0.ref.bib
pyfock/BasisSets/4zapa-nr-cv.0.tm
pyfock/BasisSets/4zapa-nr-cv.1.ref.bib
pyfock/BasisSets/4zapa-nr-cv.1.tm
pyfock/BasisSets/4zapa-nr-cv.notes
pyfock/BasisSets/4zapa-nr.0.ref.bib
pyfock/BasisSets/4zapa-nr.0.tm
pyfock/BasisSets/4zapa-nr.1.ref.bib
pyfock/BasisSets/4zapa-nr.1.tm
pyfock/BasisSets/4zapa-nr.notes
pyfock/BasisSets/5-21g.1.ref.bib
pyfock/BasisSets/5-21g.1.tm
pyfock/BasisSets/5zapa-nr-cv.0.ref.bib
pyfock/BasisSets/5zapa-nr-cv.0.tm
pyfock/BasisSets/5zapa-nr-cv.1.ref.bib
pyfock/BasisSets/5zapa-nr-cv.1.tm
pyfock/BasisSets/5zapa-nr-cv.notes
pyfock/BasisSets/5zapa-nr.0.ref.bib
pyfock/BasisSets/5zapa-nr.0.tm
pyfock/BasisSets/5zapa-nr.1.ref.bib
pyfock/BasisSets/5zapa-nr.1.tm
pyfock-0.0.9.dist-info/licenses/LICENSE
pyfock-0.0.9.dist-info/METADATA
pyfock-0.0.9.dist-info/Screenshot 2026-01-13 at 12.32.12 PM.png
pyfock-0.0.9.dist-info/WHEEL
pyfock-0.0.9.dist-info/top_level.txt
pyfock-0.0.9.dist-info/RECORD
