Metadata-Version: 2.4
Name: pyfock
Version: 0.0.9
Summary: A simplistic and efficient pure-python quantum chemistry library from Phys Whiz.
Home-page: https://github.com/manassharma07/pyfock
Download-URL: 
Author: Manas Sharma
Author-email: feedback@bragitoff.com
License: MIT
Keywords: dft,pure python,numba dft,density functional theory,manas sharma,bragitoff,quantum chemistry,pyfock,molecular integrals
Classifier: Development Status :: 5 - Production/Stable
Classifier: Topic :: Scientific/Engineering :: Chemistry
Classifier: Topic :: Scientific/Engineering :: Physics
Classifier: Intended Audience :: Science/Research
Classifier: License :: OSI Approved :: MIT License
Classifier: Programming Language :: Python :: 3 :: Only
Classifier: Programming Language :: Python :: 3.0
Classifier: Programming Language :: Python :: 3.4
Classifier: Programming Language :: Python :: 3.5
Classifier: Programming Language :: Python :: 3.6
Classifier: Programming Language :: Python :: 3.7
Classifier: Programming Language :: Python :: 3.8
Classifier: Programming Language :: Python :: 3.9
Classifier: Programming Language :: Python :: 3.10
Classifier: Programming Language :: Python :: 3.11
Classifier: Operating System :: Microsoft :: Windows
Classifier: Operating System :: Unix
Classifier: Operating System :: POSIX :: Linux
Classifier: Operating System :: MacOS :: MacOS X
License-File: LICENSE
Requires-Dist: numba>=0.57.0rc1
Requires-Dist: numexpr>=2.7.3
Requires-Dist: numba-scipy>=0.3.1
Requires-Dist: joblib>=1.2.0
Requires-Dist: numpy>=1.21.6
Requires-Dist: llvmlite>=0.40.0rc1
Requires-Dist: opt_einsum>=v3.3.0
Requires-Dist: threadpoolctl>=3.1.0
Requires-Dist: numgrid
Requires-Dist: ray
Dynamic: author
Dynamic: author-email
Dynamic: classifier
Dynamic: description
Dynamic: description-content-type
Dynamic: home-page
Dynamic: keywords
Dynamic: license
Dynamic: license-file
Dynamic: requires-dist
Dynamic: summary
